crypto_futures_py/__init__.py
crypto_futures_py/binance_futures.py
crypto_futures_py/bitmex.py
crypto_futures_py/futurespy.py
crypto_futures_py/interface.py
crypto_futures_py-0.4.3.dist-info/LICENSE
crypto_futures_py-0.4.3.dist-info/METADATA
crypto_futures_py-0.4.3.dist-info/WHEEL
crypto_futures_py-0.4.3.dist-info/top_level.txt
crypto_futures_py-0.4.3.dist-info/RECORD
