Metadata-Version: 2.1
Name: crypto-futures-py
Version: 0.4.3
Summary: The Python library of different implementations for exchange interface of cryptocurrency futures trading. Includes Bitmex and Binance Futures.
Home-page: https://github.com/LeaveMyYard/CryptoFuturesPy
Author: LeaveMyYard
Author-email: zhukovpavel2001@gmail.com
License: UNKNOWN
Project-URL: Source Code, https://github.com/LeaveMyYard/CryptoFuturesPy
Platform: UNKNOWN
Classifier: License :: OSI Approved :: Python Software Foundation License
Requires-Dist: bitmex
Requires-Dist: websocket-client
